LICENSE
LICENSE.txt
README.rst
setup.cfg
setup.py
findArea114800/__init__.py
findArea114800/findArea.py
findArea114800.egg-info/PKG-INFO
findArea114800.egg-info/SOURCES.txt
findArea114800.egg-info/dependency_links.txt
findArea114800.egg-info/top_level.txt